<pdf2xml producer="poppler" version="0.68.0">
<page height="1189" left="0" number="1" position="absolute" top="0" width="919">
	<fontspec color="#000000" family="Times" id="0" size="17" />
<image height="1189" left="0" src="XML/A7FX7D8H/A7FX7D8H.pdf-1_1.png" top="0" width="920" />
<image height="114" left="618" src="XML/A7FX7D8H/A7FX7D8H.pdf-1_2.png" top="81" width="275" />
<image height="126" left="510" src="XML/A7FX7D8H/A7FX7D8H.pdf-1_3.png" top="987" width="244" />
<text font="0" height="18" left="321" top="310" width="279">IMPRESA MANAGEMENT LLC</text>
<text font="0" height="18" left="342" top="346" width="243">FINANCIAL STATEMENTS</text>
<text font="0" height="18" left="209" top="382" width="39">FOR</text>
<text font="0" height="18" left="248" top="382" width="43">THE</text>
<text font="0" height="18" left="291" top="382" width="5" />
<text font="0" height="18" left="296" top="382" width="65">YEARS</text>
<text font="0" height="18" left="361" top="382" width="363">ENDED DECEMBER 31, 2017 AND 2016</text>
<text font="0" height="18" left="412" top="418" width="96">(Unaudited)</text>
</page>
<page height="1189" left="0" number="2" position="absolute" top="0" width="920">
	<fontspec color="#000000" family="Times" id="1" size="11" />
	<fontspec color="#000000" family="Times" id="2" size="10" />
	<fontspec color="#000000" family="Times" id="3" size="10" />
	<fontspec color="#000000" family="Times" id="4" size="13" />
	<fontspec color="#000000" family="Times" id="5" size="12" />
<image height="1190" left="0" src="XML/A7FX7D8H/A7FX7D8H.pdf-2_1.png" top="0" width="921" />
<image height="152" left="438" src="XML/A7FX7D8H/A7FX7D8H.pdf-2_2.png" top="572" width="298" />
<text font="1" height="12" left="359" top="172" width="195">IMPRESA MANAGEMENT LLC</text>
<text font="1" height="12" left="248" top="188" width="95">STATEMENTS</text>
<text font="1" height="12" left="343" top="188" width="196">OF ASSETS, LIABILITIES AND</text>
<text font="1" height="12" left="539" top="188" width="128">MEMBERS' EQUITY</text>
<text font="2" height="11" left="598" top="235" width="59"><b>12/31/2017</b></text>
<text font="2" height="11" left="657" top="235" width="3"><b> </b></text>
<text font="2" height="11" left="721" top="235" width="58"><b>12/31/2016</b></text>
<text font="3" height="11" left="124" top="249" width="34">Assets</text>
<text font="3" height="11" left="151" top="266" width="27">Cash</text>
<text font="3" height="11" left="177" top="266" width="22">and</text>
<text font="3" height="11" left="199" top="266" width="90">cash equivalents</text>
<text font="3" height="11" left="151" top="282" width="44">Related</text>
<text font="3" height="11" left="194" top="282" width="30">party</text>
<text font="3" height="11" left="225" top="282" width="53">receivable</text>
<text font="3" height="11" left="553" top="267" width="6">$</text>
<text font="3" height="11" left="602" top="266" width="52">5,916,227</text>
<text font="3" height="11" left="603" top="282" width="51">1,567,968</text>
<text font="3" height="11" left="683" top="266" width="6">$</text>
<text font="3" height="11" left="734" top="265" width="49">1,629,021</text>
<text font="3" height="11" left="743" top="282" width="42">801,590</text>
<text font="3" height="11" left="177" top="304" width="65">Total Assets</text>
<text font="3" height="11" left="553" top="305" width="5">$</text>
<text font="3" height="11" left="602" top="304" width="52">7,484,195</text>
<text font="3" height="11" left="683" top="304" width="6">$</text>
<text font="3" height="11" left="732" top="304" width="51">2,430,611</text>
<text font="3" height="11" left="126" top="344" width="53">Liabilities</text>
<text font="3" height="11" left="151" top="360" width="44">Related</text>
<text font="3" height="11" left="194" top="360" width="70">party payable</text>
<text font="3" height="11" left="151" top="376" width="95">Accrued expenses</text>
<text font="3" height="11" left="552" top="362" width="6">$</text>
<text font="3" height="11" left="601" top="360" width="53">7,154,310</text>
<text font="3" height="11" left="619" top="376" width="35">12,369</text>
<text font="3" height="11" left="682" top="361" width="6">$</text>
<text font="3" height="11" left="731" top="360" width="53">2,015,869</text>
<text font="3" height="11" left="749" top="376" width="36">30,750</text>
<text font="3" height="11" left="176" top="398" width="84">Total Liabilities</text>
<text font="3" height="11" left="601" top="398" width="52">7,166,679</text>
<text font="3" height="11" left="731" top="397" width="53">2,046,619</text>
<text font="3" height="11" left="126" top="444" width="50">Members</text>
<text font="3" height="11" left="175" top="444" width="6">&#8217;</text>
<text font="3" height="11" left="181" top="444" width="34">Equity</text>
<text font="3" height="11" left="152" top="460" width="55">Members'</text>
<text font="3" height="11" left="207" top="460" width="34">Equity</text>
<text font="3" height="11" left="552" top="461" width="5">$</text>
<text font="3" height="11" left="610" top="460" width="42">317,515</text>
<text font="3" height="11" left="681" top="460" width="6">$</text>
<text font="3" height="11" left="741" top="460" width="42">383,992</text>
<text font="3" height="11" left="176" top="482" width="27">Total</text>
<text font="3" height="11" left="204" top="482" width="59">Members'</text>
<text font="3" height="11" left="262" top="482" width="33">Equity</text>
<text font="3" height="11" left="610" top="482" width="42">317,515</text>
<text font="3" height="11" left="741" top="481" width="42">383,992</text>
<text font="3" height="11" left="177" top="504" width="27">Total</text>
<text font="3" height="11" left="204" top="504" width="4" />
<text font="3" height="11" left="207" top="504" width="79">Liabilities and</text>
<text font="3" height="11" left="286" top="504" width="88">Members' Equity</text>
<text font="3" height="11" left="552" top="505" width="5">$</text>
<text font="3" height="11" left="600" top="504" width="52">7,484,195</text>
<text font="3" height="11" left="681" top="504" width="6">$</text>
<text font="3" height="11" left="731" top="503" width="51">2,430,611</text>
<text font="4" height="14" left="487" top="732" width="31">Date</text>
<text font="5" height="13" left="518" top="732" width="5" />
<text font="4" height="14" left="523" top="732" width="67">8/24/2018</text>
<text font="3" height="11" left="451" top="1052" width="2">l</text>
</page>
<page height="1190" left="0" number="3" position="absolute" top="0" width="920">
	<fontspec color="#000000" family="Times" id="6" size="11" />
<image height="1190" left="0" src="XML/A7FX7D8H/A7FX7D8H.pdf-3_1.png" top="0" width="921" />
<image height="119" left="453" src="XML/A7FX7D8H/A7FX7D8H.pdf-3_2.png" top="710" width="375" />
<text font="5" height="13" left="346" top="163" width="64">IMPRESA</text>
<text font="4" height="14" left="410" top="163" width="5" />
<text font="4" height="14" left="415" top="163" width="113">MANAGEMENT</text>
<text font="5" height="13" left="528" top="163" width="28">LLC</text>
<text font="4" height="14" left="556" top="163" width="4" />
<text font="5" height="13" left="342" top="180" width="98">STATEMENTS</text>
<text font="4" height="14" left="439" top="180" width="5" />
<text font="5" height="13" left="444" top="180" width="18">OF</text>
<text font="4" height="14" left="463" top="180" width="4" />
<text font="5" height="13" left="467" top="180" width="93">OPERATIONS</text>
<text font="3" height="11" left="106" top="247" width="50">Revenue:</text>
<text font="6" height="12" left="611" top="231" width="28"><b>2017</b></text>
<text font="3" height="11" left="598" top="265" width="62">34,544,685</text>
<text font="6" height="12" left="696" top="263" width="6"><b>s</b></text>
<text font="6" height="12" left="746" top="229" width="27"><b>2016</b></text>
<text font="3" height="11" left="733" top="263" width="62">30,726,899</text>
<text font="3" height="11" left="132" top="264" width="71">Management</text>
<text font="3" height="11" left="203" top="264" width="44">fee and</text>
<text font="3" height="11" left="246" top="264" width="133">expense reimbursement</text>
<text font="3" height="11" left="561" top="265" width="6">$</text>
<text font="3" height="11" left="132" top="296" width="80">Total Revenue</text>
<text font="3" height="11" left="598" top="296" width="62">34,544,685</text>
<text font="3" height="11" left="733" top="295" width="61">30,726,899</text>
<text font="3" height="11" left="108" top="337" width="54">Expenses:</text>
<text font="3" height="11" left="133" top="353" width="98">Secondment costs</text>
<text font="3" height="11" left="231" top="353" width="23">and</text>
<text font="3" height="11" left="254" top="353" width="4" />
<text font="3" height="11" left="257" top="353" width="48">expense</text>
<text font="3" height="11" left="305" top="353" width="86">reimbursements</text>
<text font="3" height="11" left="560" top="353" width="6">$</text>
<text font="3" height="11" left="597" top="353" width="62">34,612,649</text>
<text font="3" height="11" left="695" top="352" width="6">$</text>
<text font="3" height="11" left="732" top="351" width="61">30,723,720</text>
<text font="3" height="11" left="133" top="370" width="84">Other expenses</text>
<text font="3" height="11" left="622" top="370" width="37">32.355</text>
<text font="3" height="11" left="750" top="367" width="47">(33,987)</text>
<text font="3" height="11" left="134" top="402" width="29">Total</text>
<text font="3" height="11" left="162" top="402" width="55">Expenses</text>
<text font="3" height="11" left="597" top="401" width="63">34,645,004</text>
<text font="3" height="11" left="732" top="400" width="61">30,689,734</text>
<text font="3" height="11" left="108" top="434" width="20">Net</text>
<text font="3" height="11" left="128" top="434" width="102">Operating Income</text>
<text font="3" height="11" left="608" top="433" width="55">(100,319)</text>
<text font="3" height="11" left="756" top="432" width="37">37,166</text>
<text font="3" height="11" left="109" top="464" width="107">Investment Income:</text>
<text font="3" height="11" left="135" top="481" width="157">Interest and dividend income</text>
<text font="3" height="11" left="560" top="481" width="6">$</text>
<text font="3" height="11" left="622" top="480" width="37">59,850</text>
<text font="3" height="11" left="694" top="480" width="6">$</text>
<text font="3" height="11" left="773" top="479" width="18">851</text>
<text font="3" height="11" left="135" top="497" width="60">Unrealized</text>
<text font="3" height="11" left="194" top="497" width="154">gainz(loss) on Investments</text>
<text font="3" height="11" left="638" top="497" width="21">249</text>
<text font="3" height="11" left="786" top="496" width="4">-</text>
<text font="3" height="11" left="134" top="514" width="21">Net</text>
<text font="3" height="11" left="154" top="514" width="136">realized gain on foreign</text>
<text font="3" height="11" left="291" top="514" width="47">currency</text>
<text font="3" height="11" left="623" top="513" width="36">13,980</text>
<text font="3" height="11" left="755" top="512" width="38">44,442</text>
<text font="3" height="11" left="135" top="530" width="41">Change</text>
<text font="3" height="11" left="176" top="530" width="94">in net unrealized</text>
<text font="3" height="11" left="270" top="530" width="4" />
<text font="3" height="11" left="274" top="530" width="134">gain on foreign currency</text>
<text font="3" height="11" left="615" top="529" width="47">(48,202)</text>
<text font="3" height="11" left="750" top="529" width="43">140,050</text>
<text font="3" height="11" left="109" top="561" width="20">Net</text>
<text font="3" height="11" left="130" top="561" width="64">Investment</text>
<text font="3" height="11" left="193" top="561" width="44">Income</text>
<text font="3" height="11" left="620" top="560" width="38">25,878</text>
<text font="3" height="11" left="749" top="560" width="42">185,342</text>
<text font="3" height="11" left="135" top="593" width="20">Net</text>
<text font="3" height="11" left="155" top="593" width="43">Income</text>
<text font="3" height="11" left="556" top="592" width="5">$</text>
<text font="3" height="11" left="615" top="592" width="47">(74,441)</text>
<text font="3" height="11" left="690" top="592" width="6">$</text>
<text font="3" height="11" left="747" top="591" width="44">222,508</text>
<text font="3" height="11" left="135" top="626" width="31">Other</text>
<text font="3" height="11" left="166" top="626" width="117">Comprehensive Loss</text>
<text font="3" height="11" left="627" top="625" width="30">7,965</text>
<text font="3" height="11" left="749" top="624" width="47">(37,750)</text>
<text font="3" height="11" left="135" top="657" width="28">Total</text>
<text font="3" height="11" left="556" top="657" width="6">$</text>
<text font="3" height="11" left="615" top="656" width="48">(66,477)</text>
<text font="3" height="11" left="690" top="657" width="6">$</text>
<text font="3" height="11" left="749" top="655" width="42">184,758</text>
<text font="3" height="11" left="449" top="1068" width="6">2</text>
</page>
</pdf2xml>